pyifc/__init__.py
pyifc/_utils.py
pyifc/compress/__init__.py
pyifc/compress/_compress.py
pyifc/compress/_exceptions.py
pyifc/compress/_pack.py
pyifc/compress/_validators.py
typings/__init__.py
pyifc-0.0.2.dist-info/LICENSE
pyifc-0.0.2.dist-info/METADATA
pyifc-0.0.2.dist-info/WHEEL
pyifc-0.0.2.dist-info/top_level.txt
pyifc-0.0.2.dist-info/RECORD
