Metadata-Version: 2.1
Name: pyifc
Version: 0.0.2
Summary: Utilities for .ifc files
Home-page: https://github.com/tbrus/pyifc
Author: tbrus
Author-email: tomek.brus1@gmail.com
License: UNKNOWN
Project-URL: Bug Tracker, https://github.com/tbrus/pyifc/issues
Platform: UNKNOWN
Classifier: Programming Language :: Python :: 3.7
Classifier: Programming Language :: Python :: 3.8
Classifier: Programming Language :: Python :: 3.9
Classifier: License :: OSI Approved :: MIT License
Classifier: Operating System :: OS Independent
Requires-Python: >=3.7
License-File: LICENSE
Requires-Dist: toposort (>=1.7)
Provides-Extra: test
Requires-Dist: pytest (>=6.0) ; extra == 'test'
Requires-Dist: coverage (>=6.0) ; extra == 'test'
